Auto3D/.gitignore
Auto3D/SPE.py
Auto3D/__init__.py
Auto3D/auto3D.py
Auto3D/auto3Dcli.py
Auto3D/isomer_engine.py
Auto3D/ranking.py
Auto3D/tautomer.py
Auto3D/utils.py
Auto3D/utils_file.py
Auto3D/ASE/__init__.py
Auto3D/ASE/geometry.py
Auto3D/ASE/thermo.py
Auto3D/ASE/__pycache__/__init__.cpython-39.pyc
Auto3D/ASE/__pycache__/geometry.cpython-39.pyc
Auto3D/ASE/__pycache__/thermo.cpython-39.pyc
Auto3D/__pycache__/SPE.cpython-39.pyc
Auto3D/__pycache__/__init__.cpython-39.pyc
Auto3D/__pycache__/auto3D.cpython-39.pyc
Auto3D/__pycache__/auto3Dcli.cpython-39.pyc
Auto3D/__pycache__/isomer_engine.cpython-39.pyc
Auto3D/__pycache__/ranking.cpython-39.pyc
Auto3D/__pycache__/tautomer.cpython-39.pyc
Auto3D/__pycache__/utils.cpython-39.pyc
Auto3D/__pycache__/utils_file.cpython-39.pyc
Auto3D/batch_opt/ANI2xt_no_rep.py
Auto3D/batch_opt/ANI2xt_rep.py
Auto3D/batch_opt/__init__.py
Auto3D/batch_opt/batchopt.py
Auto3D/batch_opt/__pycache__/ANI2xt_no_rep.cpython-39.pyc
Auto3D/batch_opt/__pycache__/__init__.cpython-39.pyc
Auto3D/batch_opt/__pycache__/batchopt.cpython-39.pyc
Auto3D/models/__init__.py
Auto3D/models/aimnet2_wb97m-d3_0.jpt
Auto3D/models/aimnet2_wb97m_ens_f.jpt
Auto3D/models/ani2xt_no_repulsion.pt
Auto3D-2.3.1.dist-info/LICENSE
Auto3D-2.3.1.dist-info/METADATA
Auto3D-2.3.1.dist-info/WHEEL
Auto3D-2.3.1.dist-info/entry_points.txt
Auto3D-2.3.1.dist-info/top_level.txt
Auto3D-2.3.1.dist-info/RECORD
