Metadata-Version: 2.1
Name: Auto3D
Version: 2.3.1
Summary: Generating Low-energy 3D Conformers from SMILES/SDF
Home-page: https://github.com/isayevlab/Auto3D_pkg
Author: 'Zhen Liu, Tetiana Zubatiuk, Adrian Roitberg, Olexandr Isayev'
Author-email: liu5@andrew.cmu.edu, tetiana@zubatyuk.com, roitberg@ufl.edu, olexandr@olexandrisayev.com
Project-URL: Bug Tracker, https://github.com/isayevlab/Auto3D_pkg/issues
Classifier: Programming Language :: Python :: 3
Classifier: License :: OSI Approved :: MIT License
Classifier: Operating System :: OS Independent
Requires-Python: >=3.7
License-File: LICENSE
Requires-Dist: tqdm
Requires-Dist: psutil
Requires-Dist: Send2Trash
Requires-Dist: pyyaml
